{
  "preserveForPublish": true,
  "opfPath": "EPUB/content.opf",
  "defaultViewportWidth": 1575,
  "defaultViewportHeight": 2325,
  "spine": [
    {
      "pageNumber": 1,
      "manifestId": "page1",
      "href": "page1.xhtml",
      "xhtmlPathFromEpubRoot": "EPUB/page1.xhtml"
    },
    {
      "pageNumber": 2,
      "manifestId": "page2",
      "href": "page2.xhtml",
      "xhtmlPathFromEpubRoot": "EPUB/page2.xhtml"
    },
    {
      "pageNumber": 3,
      "manifestId": "page3",
      "href": "page3.xhtml",
      "xhtmlPathFromEpubRoot": "EPUB/page3.xhtml"
    },
    {
      "pageNumber": 4,
      "manifestId": "page4",
      "href": "page4.xhtml",
      "xhtmlPathFromEpubRoot": "EPUB/page4.xhtml"
    },
    {
      "pageNumber": 5,
      "manifestId": "page5",
      "href": "page5.xhtml",
      "xhtmlPathFromEpubRoot": "EPUB/page5.xhtml"
    },
    {
      "pageNumber": 6,
      "manifestId": "page6",
      "href": "page6.xhtml",
      "xhtmlPathFromEpubRoot": "EPUB/page6.xhtml"
    },
    {
      "pageNumber": 7,
      "manifestId": "page7",
      "href": "page7.xhtml",
      "xhtmlPathFromEpubRoot": "EPUB/page7.xhtml"
    },
    {
      "pageNumber": 8,
      "manifestId": "page8",
      "href": "page8.xhtml",
      "xhtmlPathFromEpubRoot": "EPUB/page8.xhtml"
    },
    {
      "pageNumber": 9,
      "manifestId": "page9",
      "href": "page9.xhtml",
      "xhtmlPathFromEpubRoot": "EPUB/page9.xhtml"
    },
    {
      "pageNumber": 10,
      "manifestId": "page10",
      "href": "page10.xhtml",
      "xhtmlPathFromEpubRoot": "EPUB/page10.xhtml"
    },
    {
      "pageNumber": 11,
      "manifestId": "page11",
      "href": "page11.xhtml",
      "xhtmlPathFromEpubRoot": "EPUB/page11.xhtml"
    },
    {
      "pageNumber": 12,
      "manifestId": "page12",
      "href": "page12.xhtml",
      "xhtmlPathFromEpubRoot": "EPUB/page12.xhtml"
    },
    {
      "pageNumber": 13,
      "manifestId": "page13",
      "href": "page13.xhtml",
      "xhtmlPathFromEpubRoot": "EPUB/page13.xhtml"
    },
    {
      "pageNumber": 14,
      "manifestId": "page14",
      "href": "page14.xhtml",
      "xhtmlPathFromEpubRoot": "EPUB/page14.xhtml"
    },
    {
      "pageNumber": 15,
      "manifestId": "page15",
      "href": "page15.xhtml",
      "xhtmlPathFromEpubRoot": "EPUB/page15.xhtml"
    },
    {
      "pageNumber": 16,
      "manifestId": "page16",
      "href": "page16.xhtml",
      "xhtmlPathFromEpubRoot": "EPUB/page16.xhtml"
    },
    {
      "pageNumber": 17,
      "manifestId": "page17",
      "href": "page17.xhtml",
      "xhtmlPathFromEpubRoot": "EPUB/page17.xhtml"
    },
    {
      "pageNumber": 18,
      "manifestId": "page18",
      "href": "page18.xhtml",
      "xhtmlPathFromEpubRoot": "EPUB/page18.xhtml"
    },
    {
      "pageNumber": 19,
      "manifestId": "page19",
      "href": "page19.xhtml",
      "xhtmlPathFromEpubRoot": "EPUB/page19.xhtml"
    },
    {
      "pageNumber": 20,
      "manifestId": "page20",
      "href": "page20.xhtml",
      "xhtmlPathFromEpubRoot": "EPUB/page20.xhtml"
    },
    {
      "pageNumber": 21,
      "manifestId": "page21",
      "href": "page21.xhtml",
      "xhtmlPathFromEpubRoot": "EPUB/page21.xhtml"
    },
    {
      "pageNumber": 22,
      "manifestId": "page22",
      "href": "page22.xhtml",
      "xhtmlPathFromEpubRoot": "EPUB/page22.xhtml"
    },
    {
      "pageNumber": 23,
      "manifestId": "page23",
      "href": "page23.xhtml",
      "xhtmlPathFromEpubRoot": "EPUB/page23.xhtml"
    },
    {
      "pageNumber": 24,
      "manifestId": "page24",
      "href": "page24.xhtml",
      "xhtmlPathFromEpubRoot": "EPUB/page24.xhtml"
    },
    {
      "pageNumber": 25,
      "manifestId": "page25",
      "href": "page25.xhtml",
      "xhtmlPathFromEpubRoot": "EPUB/page25.xhtml"
    },
    {
      "pageNumber": 26,
      "manifestId": "page26",
      "href": "page26.xhtml",
      "xhtmlPathFromEpubRoot": "EPUB/page26.xhtml"
    },
    {
      "pageNumber": 27,
      "manifestId": "page27",
      "href": "page27.xhtml",
      "xhtmlPathFromEpubRoot": "EPUB/page27.xhtml"
    },
    {
      "pageNumber": 28,
      "manifestId": "page28",
      "href": "page28.xhtml",
      "xhtmlPathFromEpubRoot": "EPUB/page28.xhtml"
    },
    {
      "pageNumber": 29,
      "manifestId": "page29",
      "href": "page29.xhtml",
      "xhtmlPathFromEpubRoot": "EPUB/page29.xhtml"
    },
    {
      "pageNumber": 30,
      "manifestId": "page30",
      "href": "page30.xhtml",
      "xhtmlPathFromEpubRoot": "EPUB/page30.xhtml"
    }
  ]
}