{
  "totalFragments": 14,
  "fragments": [
    {
      "begin": "0.000",
      "end": "0.080",
      "lines": [
        "If"
      ],
      "id": "f000001"
    },
    {
      "begin": "0.080",
      "end": "0.480",
      "lines": [
        "You"
      ],
      "id": "f000002"
    },
    {
      "begin": "0.480",
      "end": "0.920",
      "lines": [
        "Were"
      ],
      "id": "f000003"
    },
    {
      "begin": "0.920",
      "end": "1.440",
      "lines": [
        "a"
      ],
      "id": "f000004"
    },
    {
      "begin": "1.440",
      "end": "1.640",
      "lines": [
        "Horse"
      ],
      "id": "f000005"
    },
    {
      "begin": "1.640",
      "end": "2.200",
      "lines": [
        "Have"
      ],
      "id": "f000006"
    },
    {
      "begin": "2.200",
      "end": "2.480",
      "lines": [
        "you"
      ],
      "id": "f000007"
    },
    {
      "begin": "2.480",
      "end": "2.800",
      "lines": [
        "ever"
      ],
      "id": "f000008"
    },
    {
      "begin": "2.800",
      "end": "3.200",
      "lines": [
        "wished"
      ],
      "id": "f000009"
    },
    {
      "begin": "3.200",
      "end": "3.600",
      "lines": [
        "you"
      ],
      "id": "f000010"
    }
  ]
}